installutils/__init__.py
installutils/util.py
installutils_nohookwheel-1.0.0.dist-info/METADATA
installutils_nohookwheel-1.0.0.dist-info/WHEEL
installutils_nohookwheel-1.0.0.dist-info/top_level.txt
installutils_nohookwheel-1.0.0.dist-info/RECORD
