Metadata-Version: 2.1
Name: installutils-nohookwheel
Version: 1.0.0
Summary: a template for executing build steps on package install - nohookwheel version
Home-page: https://github.com/acamach0/installutils
Author: The InstallUtils Team
Author-email: 44acamach0@gmail.com
License: GPLv3
Platform: UNKNOWN
Classifier: Environment :: Console
Classifier: License :: OSI Approved :: GNU General Public License v3 (GPLv3)
Classifier: Operating System :: MacOS :: MacOS X
Classifier: Operating System :: Microsoft :: Windows
Classifier: Operating System :: POSIX
